{
   "html_attributions" : [],
   "result" : {
      "address_components" : [
         {
            "long_name" : "940",
            "short_name" : "940",
            "types" : [ "street_number" ]
         },
         {
            "long_name" : "Garrison Avenue",
            "short_name" : "Garrison Ave",
            "types" : [ "route" ]
         },
         {
            "long_name" : "Hunts Point",
            "short_name" : "Hunts Point",
            "types" : [ "neighborhood", "political" ]
         },
         {
            "long_name" : "The Bronx",
            "short_name" : "The Bronx",
            "types" : [ "sublocality_level_1", "sublocality", "political" ]
         },
         {
            "long_name" : "Bronx County",
            "short_name" : "Bronx County",
            "types" : [ "administrative_area_level_2", "political" ]
         },
         {
            "long_name" : "New York",
            "short_name" : "NY",
            "types" : [ "administrative_area_level_1", "political" ]
         },
         {
            "long_name" : "United States",
            "short_name" : "US",
            "types" : [ "country", "political" ]
         },
         {
            "long_name" : "10474",
            "short_name" : "10474",
            "types" : [ "postal_code" ]
         }
      ],
      "adr_address" : "\u003cspan class=\"street-address\"\u003e940 Garrison Ave\u003c/span\u003e, \u003cspan class=\"locality\"\u003eThe Bronx\u003c/span\u003e, \u003cspan class=\"region\"\u003eNY\u003c/span\u003e \u003cspan class=\"postal-code\"\u003e10474\u003c/span\u003e, \u003cspan class=\"country-name\"\u003eUSA\u003c/span\u003e",
      "business_status" : "CLOSED_TEMPORARILY",
      "formatted_address" : "940 Garrison Ave, The Bronx, NY 10474, USA",
      "formatted_phone_number" : "(718) 542-4139 ext. 175",
      "geometry" : {
         "location" : {
            "lat" : 40.8182031,
            "lng" : -73.8905065
         },
         "viewport" : {
            "northeast" : {
               "lat" : 40.8196308802915,
               "lng" : -73.8892911697085
            },
            "southwest" : {
               "lat" : 40.81693291970851,
               "lng" : -73.89198913029151
            }
         }
      },
      "icon" : "https://maps.gstatic.com/mapfiles/place_api/icons/v1/png_71/generic_business-71.png",
      "international_phone_number" : "+1 718-542-4139 ext. 175",
      "name" : "Open Hydrant Theatre",
      "permanently_closed" : true,
      "photos" : [
         {
            "height" : 4160,
            "html_attributions" : [
               "\u003ca href=\"https://maps.google.com/maps/contrib/102555028316500379351\"\u003eMaribelle Vazquez\u003c/a\u003e"
            ],
            "photo_reference" : "ATtYBwJzcN-HR2hm6lCOQ3AQYyo6sLfOg8da5qFFrTOVBDf68fMzVZh0Nxt2UCU7hU4ee62Psm1gmuwEjcHoYIooE--HhQbDK56Wmqs5qZcWEzVuS_nuVavPiC_EVms-FrpyjlO7_AhlpBqGuzxty-zf4fUvFFtDdFyIeHcqxQIJOzUbjM4V",
            "width" : 2340
         },
         {
            "height" : 4160,
            "html_attributions" : [
               "\u003ca href=\"https://maps.google.com/maps/contrib/102555028316500379351\"\u003eMaribelle Vazquez\u003c/a\u003e"
            ],
            "photo_reference" : "ATtYBwLKzQIaAr1VVSAKYznR4GpLOvi2JNQ7t7MbmYnj-hrsRNgbqsZ6x1LLr2PUXNDklG-XiNXxLkxXxUKrWxWawqVHbOdr9f67TVBtb2g_ClWktBG2X-OXwb-z-SVJxQFfOK7DnLhMGHK3NlLTJZYG0CdmJiIoO9apASRIREH_JvX3o3cd",
            "width" : 2340
         },
         {
            "height" : 2340,
            "html_attributions" : [
               "\u003ca href=\"https://maps.google.com/maps/contrib/102555028316500379351\"\u003eMaribelle Vazquez\u003c/a\u003e"
            ],
            "photo_reference" : "ATtYBwJbVIu1c1WKG3d-AbWmG9-JHTX_Ww4QAxcmxIxZLtFYH_hEeNTgqGW-5PSuJCwo0Say4nvMLAJ88OjPR9bBoTRzaMMEUMfp6yiAVMELPZgU7IzAjfBD9u-LOISkhbcsYzg8e0PNh3vwZ9UdStcYMd9O6YZ808GhZZ4uf53nFQby56AL",
            "width" : 4160
         },
         {
            "height" : 4160,
            "html_attributions" : [
               "\u003ca href=\"https://maps.google.com/maps/contrib/102555028316500379351\"\u003eMaribelle Vazquez\u003c/a\u003e"
            ],
            "photo_reference" : "ATtYBwK3A1tkkAlTP3Ba1SdFYfWdL5GHJiS1v6xf4aAMeE7l74bPdkCqyyij5pkxKxDCrCm1otEoq-Fr4FSHMiuDGOqYcv9zciCNT3v198eP0o_C3r2rR1nIzFvrVZHvmQBsndwI5_9wUqIj-0g0WDip7s9mHOIf7PRDdZXCR15l8gzgY-Bz",
            "width" : 2340
         }
      ],
      "place_id" : "ChIJqT0VXqr1wokRAjhW6GZkvqQ",
      "plus_code" : {
         "compound_code" : "R495+7Q The Bronx, NY, USA",
         "global_code" : "87G8R495+7Q"
      },
      "rating" : 4.7,
      "reference" : "ChIJqT0VXqr1wokRAjhW6GZkvqQ",
      "reviews" : [
         {
            "author_name" : "Leah Z",
            "author_url" : "https://www.google.com/maps/contrib/104927697899623326518/reviews",
            "language" : "en",
            "profile_photo_url" : "https://lh5.googleusercontent.com/-KrZrNor8lj0/AAAAAAAAAAI/AAAAAAAAAAA/AMZuucnem_k63oR58QaZBNUIhfksJ2niBw/s128-c0x00000000-cc-rp-mo-ba3/photo.jpg",
            "rating" : 5,
            "relative_time_description" : "a year ago",
            "text" : "Wonderful theater family with truly dedicated owners. They do a fabulous job of encouraging the arts in the Bronx. My daughter is learning so much about theater & skills not typically taught at other establishments.",
            "time" : 1552186117
         },
         {
            "author_name" : "Edison Pozo",
            "author_url" : "https://www.google.com/maps/contrib/100312362187054995730/reviews",
            "language" : "en",
            "profile_photo_url" : "https://lh4.googleusercontent.com/-XCatb5Fkhn8/AAAAAAAAAAI/AAAAAAAAAAA/AMZuuck2mPkX0SR5dLAGKFwNtQFTl0Q7jw/s128-c0x00000000-cc-rp-mo/photo.jpg",
            "rating" : 5,
            "relative_time_description" : "2 years ago",
            "text" : "Just seen, \"WEST SIDE STORY\"\nThese kids are so talented, AWESOME!!!\nWill definitely make time to see all upcoming performances. AWESOME!",
            "time" : 1537676575
         },
         {
            "author_name" : "MISS MONEE",
            "author_url" : "https://www.google.com/maps/contrib/116516142206766818218/reviews",
            "language" : "en",
            "profile_photo_url" : "https://lh3.googleusercontent.com/a-/AOh14GhUz_HsHv-4rNs44rz8LpumLpazxfpivTRr9WRZ7Q=s128-c0x00000000-cc-rp-mo-ba4",
            "rating" : 5,
            "relative_time_description" : "2 years ago",
            "text" : "Always love doing performances with the people their. Love to watch their amazing plays too. You should try out for the other activities!",
            "time" : 1529168657
         },
         {
            "author_name" : "ALICIA HARRIS",
            "author_url" : "https://www.google.com/maps/contrib/118039655895296853426/reviews",
            "language" : "en",
            "profile_photo_url" : "https://lh3.googleusercontent.com/a-/AOh14Gg3kt1PgThBuaVIEBt0uEGhabnZYuuI9xoWIsFVOw=s128-c0x00000000-cc-rp-mo",
            "rating" : 5,
            "relative_time_description" : "a year ago",
            "text" : "Awesome place for kids to find talent and somewhere safe to go",
            "time" : 1556938397
         },
         {
            "author_name" : "Maribelle Vazquez",
            "author_url" : "https://www.google.com/maps/contrib/102555028316500379351/reviews",
            "language" : "en",
            "profile_photo_url" : "https://lh3.googleusercontent.com/a-/AOh14Gg8jOkFYU7IUvIfN_hb40ryudGCWlBzk_Q78AN75w=s128-c0x00000000-cc-rp-mo",
            "rating" : 5,
            "relative_time_description" : "2 years ago",
            "text" : "Great performance space.",
            "time" : 1522722435
         }
      ],
      "types" : [ "point_of_interest", "establishment" ],
      "url" : "https://maps.google.com/?cid=11871036060942612482",
      "user_ratings_total" : 14,
      "utc_offset" : -300,
      "vicinity" : "940 Garrison Avenue, The Bronx",
      "website" : "http://www.openhydrant.org/"
   },
   "status" : "OK"
}
